concierge/__init__.py
concierge/config.py
concierge_workflows-0.1.0.dist-info/licenses/LICENSE
concierge_workflows-0.1.0.dist-info/METADATA
concierge_workflows-0.1.0.dist-info/WHEEL
concierge_workflows-0.1.0.dist-info/top_level.txt
concierge_workflows-0.1.0.dist-info/RECORD
