Metadata-Version: 2.4
Name: concierge-workflows
Version: 0.1.0
Summary: Declarative framework for building Agentic AI Services
License: # License
Project-URL: Homepage, https://github.com/Agentic-Web-Interfaces/concierge
Project-URL: Repository, https://github.com/Agentic-Web-Interfaces/concierge
Requires-Python: >=3.9
License-File: LICENSE
Requires-Dist: fastapi>=0.104.0
Requires-Dist: uvicorn>=0.24.0
Requires-Dist: pydantic>=2.0.0
Requires-Dist: pyyaml>=6.0
Requires-Dist: requests>=2.31.0
Dynamic: license-file
